hydroland/__init__.py
hydroland/_version.py
hydroland/completion.py
hydroland/data_preparation.py
hydroland/initialisation.py
hydroland/mhm.py
hydroland/mhm_setup.py
hydroland/mrm.py
hydroland/mrm_setup.py
hydroland/preprocessing.py
hydroland/_cli/__init__.py
hydroland/_cli/_main.py
hydroland-1.1.1.dist-info/METADATA
hydroland-1.1.1.dist-info/WHEEL
hydroland-1.1.1.dist-info/entry_points.txt
hydroland-1.1.1.dist-info/licenses/COPYING
hydroland-1.1.1.dist-info/licenses/COPYING.LESSER
hydroland-1.1.1.dist-info/licenses/LICENSE.md
hydroland-1.1.1.dist-info/RECORD
