Metadata-Version: 2.4
Name: hydroland
Version: 1.1.1
Summary: Hydroland application package for Climate Change Adaptation Digital Twin | Destination Earth.
Author-email: Jeisson Leal <jeisson-javier.leal-rojas@ufz.de>, Sebastian Müller <sebastian.mueller@ufz.de>, Stephan Thober <stephan.thober@ufz.de>
License-Expression: LGPL-3.0
License-File: COPYING
License-File: COPYING.LESSER
License-File: LICENSE.md
Classifier: Development Status :: 4 - Beta
Classifier: Intended Audience :: Developers
Classifier: Intended Audience :: End Users/Desktop
Classifier: Intended Audience :: Science/Research
Classifier: License :: OSI Approved :: GNU Lesser General Public License v3 (LGPLv3)
Classifier: Natural Language :: English
Classifier: Operating System :: MacOS
Classifier: Operating System :: Microsoft
Classifier: Operating System :: Unix
Classifier: Programming Language :: Python
Classifier: Programming Language :: Python :: 3
Classifier: Programming Language :: Python :: 3 :: Only
Classifier: Topic :: Scientific/Engineering
Classifier: Topic :: Software Development
Classifier: Topic :: Utilities
Requires-Python: >=3.9
Requires-Dist: crick
Requires-Dist: fypp
Requires-Dist: isort
Requires-Dist: matplotlib
Requires-Dist: netcdf4
Requires-Dist: numpy>=1.17.0
Requires-Dist: pandas
Requires-Dist: pytest
Requires-Dist: pytest-mock
Requires-Dist: ruff
Requires-Dist: scipy
Requires-Dist: xarray
